etc/monasca/api-config.ini
etc/monasca/api-logging.conf
monasca_api/__init__.py
monasca_api/config.py
monasca_api/healthchecks.py
monasca_api/version.py
monasca_api/api/__init__.py
monasca_api/api/alarm_definitions_api_v2.py
monasca_api/api/alarms_api_v2.py
monasca_api/api/healthcheck_api.py
monasca_api/api/logs_api.py
monasca_api/api/metrics_api_v2.py
monasca_api/api/notifications_api_v2.py
monasca_api/api/notificationstype_api_v2.py
monasca_api/api/server.py
monasca_api/api/versions_api.py
monasca_api/api/wsgi.py
monasca_api/api/core/__init__.py
monasca_api/api/core/request.py
monasca_api/api/core/request_context.py
monasca_api/api/core/log/__init__.py
monasca_api/api/core/log/exceptions.py
monasca_api/api/core/log/log_publisher.py
monasca_api/api/core/log/model.py
monasca_api/api/core/log/validation.py
monasca_api/cmd/__init__.py
monasca_api/cmd/monasca_db.py
monasca_api/cmd/status.py
monasca_api/common/__init__.py
monasca_api/common/messaging/__init__.py
monasca_api/common/messaging/exceptions.py
monasca_api/common/messaging/fake_publisher.py
monasca_api/common/messaging/kafka_publisher.py
monasca_api/common/messaging/publisher.py
monasca_api/common/messaging/message_formats/__init__.py
monasca_api/common/messaging/message_formats/metrics.py
monasca_api/common/policy/__init__.py
monasca_api/common/policy/i18n.py
monasca_api/common/policy/policy_engine.py
monasca_api/common/repositories/__init__.py
monasca_api/common/repositories/alarm_definitions_repository.py
monasca_api/common/repositories/alarms_repository.py
monasca_api/common/repositories/constants.py
monasca_api/common/repositories/exceptions.py
monasca_api/common/repositories/metrics_repository.py
monasca_api/common/repositories/notification_method_type_repository.py
monasca_api/common/repositories/notifications_repository.py
monasca_api/common/repositories/cassandra/__init__.py
monasca_api/common/repositories/cassandra/metrics_repository.py
monasca_api/common/repositories/fake/__init__.py
monasca_api-11.0.0.dist-info/AUTHORS
monasca_api-11.0.0.dist-info/LICENSE
monasca_api-11.0.0.dist-info/METADATA
monasca_api-11.0.0.dist-info/WHEEL
monasca_api-11.0.0.dist-info/entry_points.txt
monasca_api-11.0.0.dist-info/pbr.json
monasca_api-11.0.0.dist-info/top_level.txt
monasca_api-11.0.0.dist-info/RECORD
