Metadata-Version: 2.1
Name: monasca-api
Version: 11.0.0
Summary: OpenStack Monitoring as a Service
Home-page: https://docs.openstack.org/monasca-api/latest/
Author: OpenStack
Author-email: openstack-discuss@lists.openstack.org
License: UNKNOWN
Platform: UNKNOWN
Classifier: Environment :: OpenStack
Classifier: Intended Audience :: Information Technology
Classifier: Intended Audience :: System Administrators
Classifier: License :: OSI Approved :: Apache Software License
Classifier: Operating System :: POSIX :: Linux
Classifier: Programming Language :: Python
Classifier: Programming Language :: Python :: Implementation :: CPython
Classifier: Programming Language :: Python :: 3 :: Only
Classifier: Programming Language :: Python :: 3.6
Classifier: Programming Language :: Python :: 3.7
Classifier: Programming Language :: Python :: 3.8
Requires-Python: >=3.6
Requires-Dist: Paste (>=2.0.2)
Requires-Dist: PasteDeploy (>=1.5.0)
Requires-Dist: SQLAlchemy (>=1.3.0)
Requires-Dist: eventlet (!=0.18.3,!=0.20.1,!=0.21.0,!=0.23.0,!=0.25.0,>=0.18.2)
Requires-Dist: falcon (>=2.0.0)
Requires-Dist: keystonemiddleware (>=4.17.0)
Requires-Dist: monasca-common (>=2.16.0)
Requires-Dist: oslo.config (>=6.8.0)
Requires-Dist: oslo.context (>=2.22.0)
Requires-Dist: oslo.db (>=6.0.0)
Requires-Dist: oslo.log (>=3.36.0)
Requires-Dist: oslo.middleware (>=3.31.0)
Requires-Dist: oslo.policy (>=3.6.0)
Requires-Dist: oslo.serialization (!=2.19.1,>=2.18.0)
Requires-Dist: oslo.upgradecheck (>=1.3.0)
Requires-Dist: oslo.utils (>=4.5.0)
Requires-Dist: pbr (!=2.1.0,>=2.0.0)
Requires-Dist: pyparsing (>=3.0.6)
Requires-Dist: python-keystoneclient (>=3.8.0)
Requires-Dist: simplejson (>=3.8.1)
Requires-Dist: six (>=1.12.0)
Requires-Dist: voluptuous (>=0.11.1)
Provides-Extra: cassandra
Requires-Dist: cassandra-driver (!=3.6.0,>=3.3.0) ; extra == 'cassandra'
Provides-Extra: influxdb
Requires-Dist: influxdb (>=2.9.2) ; extra == 'influxdb'
Provides-Extra: test
Requires-Dist: Babel (!=2.4.0,>=2.3.4) ; extra == 'test'
Requires-Dist: bandit (>=1.1.0) ; extra == 'test'
Requires-Dist: bashate (>=0.5.1) ; extra == 'test'
Requires-Dist: cassandra-driver (!=3.6.0,>=3.3.0) ; extra == 'test'
Requires-Dist: coverage (!=4.4,>=4.0) ; extra == 'test'
Requires-Dist: doc8 (>=0.6.0) ; extra == 'test'
Requires-Dist: fixtures (>=3.0.0) ; extra == 'test'
Requires-Dist: hacking (<3.1.0,>=3.0.1) ; extra == 'test'
Requires-Dist: httplib2 (>=0.9.1) ; extra == 'test'
Requires-Dist: influxdb (>=2.9.2) ; extra == 'test'
Requires-Dist: oslotest (>=3.2.0) ; extra == 'test'
Requires-Dist: python-subunit (>=1.0.0) ; extra == 'test'
Requires-Dist: requests-mock (>=1.2.0) ; extra == 'test'
Requires-Dist: stestr (>=1.0.0) ; extra == 'test'
Requires-Dist: tempest (>=17.1.0) ; extra == 'test'
Requires-Dist: testrepository (>=0.0.18) ; extra == 'test'
Requires-Dist: testscenarios (>=0.4) ; extra == 'test'
Requires-Dist: testtools (>=2.2.0) ; extra == 'test'
